hketa/__init__.py
hketa/_gtfs_parser.py
hketa/_utils.py
hketa/ctb.py
hketa/kmb.py
hketa/lrt.py
hketa/lrtfeeder.py
hketa/mtr.py
hketa/nlb.py
hketa/t.py
hketa-0.0.6.dist-info/LICENSE
hketa-0.0.6.dist-info/METADATA
hketa-0.0.6.dist-info/WHEEL
hketa-0.0.6.dist-info/top_level.txt
hketa-0.0.6.dist-info/RECORD
