Metadata-Version: 2.1
Name: hketa
Version: 0.0.6
Summary: A Python package that provides normalised data access to public transports in Hong Kong.
Home-page: https://github.com/SuperDumbTM/hketa
License-File: LICENSE
Requires-Dist: aiohttp
Requires-Dist: beautifulsoup4
Requires-Dist: pyproj
Requires-Dist: pytz
